plsre/PlsRegression.py
plsre/__init__.py
plsRe-0.0.2.dist-info/LICENSE
plsRe-0.0.2.dist-info/METADATA
plsRe-0.0.2.dist-info/WHEEL
plsRe-0.0.2.dist-info/top_level.txt
plsRe-0.0.2.dist-info/RECORD
