Metadata-Version: 2.1
Name: plsRe
Version: 0.0.2
Summary: A simple package for Partial Least-Sqaures Regression
Home-page: https://github.com/ychen381/PLSR
Author: Charles Chen
Author-email: yc414@duke.edu
License: UNKNOWN
Keywords: package models regression
Platform: UNKNOWN
Classifier: Programming Language :: Python :: 3
Classifier: Operating System :: OS Independent
